simple_dependency_injection/__init__.py
simple_dependency_injection/dependency_container.py
simple_dependency_injection-0.1.6.dist-info/LICENSE
simple_dependency_injection-0.1.6.dist-info/WHEEL
simple_dependency_injection-0.1.6.dist-info/METADATA
simple_dependency_injection-0.1.6.dist-info/RECORD
